sandeep_keyword_generator/__init__.py
sandeep_keyword_generator/extractor.py
sandeep_keyword_generator-0.1.dist-info/METADATA
sandeep_keyword_generator-0.1.dist-info/WHEEL
sandeep_keyword_generator-0.1.dist-info/top_level.txt
sandeep_keyword_generator-0.1.dist-info/RECORD
